{"progress": 86, "message": "Processing clips 231-235/264...", "status": "processing", "logs": "[18:40:39] Processing clips 86-90/264...\n[18:40:51] Processing clips 91-95/264...\n[18:41:08] Processing clips 96-100/264...\n[18:41:22] Processing clips 101-105/264...\n[18:41:34] Processing clips 106-110/264...\n[18:41:42] Processing clips 111-115/264...\n[18:41:51] Processing clips 116-120/264...\n[18:41:59] Processing clips 121-125/264...\n[18:42:08] Processing clips 126-130/264...\n[18:42:16] Processing clips 131-135/264...\n[18:42:24] Processing clips 136-140/264...\n[18:42:32] Processing clips 141-145/264...\n[18:42:41] Processing clips 146-150/264...\n[18:42:51] Processing clips 151-155/264...\n[18:42:58] Processing clips 156-160/264...\n[18:43:06] Processing clips 161-165/264...\n[18:43:16] Processing clips 166-170/264...\n[18:43:24] Processing clips 171-175/264...\n[18:43:35] Processing clips 176-180/264...\n[18:43:43] Processing clips 181-185/264...\n[18:43:59] Processing clips 186-190/264...\n[18:44:12] Processing clips 191-195/264...\n[18:44:23] Processing clips 196-200/264...\n[18:44:33] Processing clips 201-205/264...\n[18:44:46] Processing clips 206-210/264...\n[18:44:56] Processing clips 211-215/264...\n[18:45:16] Processing clips 216-220/264...\n[18:45:28] Processing clips 221-225/264...\n[18:45:40] Processing clips 226-230/264...\n[18:45:48] Processing clips 231-235/264...", "timestamp": 1766342748.6922047}