{"progress": 83, "message": "Completed 220/231 clips", "status": "processing", "logs": "[15:58:51] Completed 191/231 clips\n[15:58:52] Completed 192/231 clips\n[15:58:56] Completed 193/231 clips\n[15:58:57] Completed 194/231 clips\n[15:58:58] Completed 195/231 clips\n[15:59:01] Completed 196/231 clips\n[15:59:02] Completed 197/231 clips\n[15:59:06] Completed 198/231 clips\n[15:59:06] Completed 199/231 clips\n[15:59:08] Completed 200/231 clips\n[15:59:09] Completed 201/231 clips\n[15:59:11] Completed 202/231 clips\n[15:59:15] Completed 203/231 clips\n[15:59:16] Completed 204/231 clips\n[15:59:17] Completed 205/231 clips\n[15:59:18] Completed 206/231 clips\n[15:59:20] Completed 207/231 clips\n[15:59:22] Completed 208/231 clips\n[15:59:24] Completed 209/231 clips\n[15:59:25] Completed 210/231 clips\n[15:59:27] Completed 211/231 clips\n[15:59:29] Completed 212/231 clips\n[15:59:30] Completed 213/231 clips\n[15:59:31] Completed 214/231 clips\n[15:59:32] Completed 215/231 clips\n[15:59:35] Completed 216/231 clips\n[15:59:36] Completed 217/231 clips\n[15:59:36] Completed 218/231 clips\n[15:59:42] Completed 219/231 clips\n[15:59:43] Completed 220/231 clips", "timestamp": 1767196783.2270083}