{"progress": 75, "message": "Completed 154/245 clips", "status": "processing", "logs": "[15:46:29] Completed 125/245 clips\n[15:46:30] Completed 126/245 clips\n[15:46:31] Completed 127/245 clips\n[15:46:34] Completed 128/245 clips\n[15:46:35] Completed 129/245 clips\n[15:46:36] Completed 130/245 clips\n[15:46:37] Completed 131/245 clips\n[15:46:38] Completed 132/245 clips\n[15:46:39] Completed 133/245 clips\n[15:46:41] Completed 134/245 clips\n[15:46:43] Completed 135/245 clips\n[15:46:44] Completed 136/245 clips\n[15:46:45] Completed 137/245 clips\n[15:46:45] Completed 138/245 clips\n[15:46:50] Completed 139/245 clips\n[15:46:50] Completed 140/245 clips\n[15:46:51] Completed 141/245 clips\n[15:46:52] Completed 142/245 clips\n[15:46:53] Completed 143/245 clips\n[15:46:57] Completed 144/245 clips\n[15:46:57] Completed 145/245 clips\n[15:46:59] Completed 146/245 clips\n[15:47:00] Completed 147/245 clips\n[15:47:01] Completed 148/245 clips\n[15:47:05] Completed 149/245 clips\n[15:47:07] Completed 150/245 clips\n[15:47:08] Completed 151/245 clips\n[15:47:09] Completed 152/245 clips\n[15:47:11] Completed 153/245 clips\n[15:47:15] Completed 154/245 clips", "timestamp": 1766936835.3609107}