{"progress": 73, "message": "Processing clips 121-125/264...", "status": "processing", "logs": "[16:25:56] Initializing SubMagic-level engine...\n[16:26:00] Generating script with Gemini...\n[16:26:01] Creating timeline with semantic analysis...\n[16:26:02] Starting parallel audio generation...\n[16:26:03] Starting SubMagic-level video processing...\n[16:26:04] Processing clips 1-5/264...\n[16:26:06] Processing clips 6-10/264...\n[16:26:07] Processing clips 11-15/264...\n[16:26:08] Processing clips 16-20/264...\n[16:26:09] Processing clips 21-25/264...\n[16:26:11] Processing clips 26-30/264...\n[16:26:12] Processing clips 31-35/264...\n[16:26:13] Processing clips 36-40/264...\n[16:26:16] Processing clips 41-45/264...\n[16:26:18] Processing clips 46-50/264...\n[16:26:19] Processing clips 51-55/264...\n[16:26:20] Processing clips 56-60/264...\n[16:26:21] Processing clips 61-65/264...\n[16:26:22] Processing clips 66-70/264...\n[16:26:23] Processing clips 71-75/264...\n[16:26:25] Processing clips 76-80/264...\n[16:26:26] Processing clips 81-85/264...\n[16:26:27] Processing clips 86-90/264...\n[16:26:29] Processing clips 91-95/264...\n[16:26:30] Processing clips 96-100/264...\n[16:26:31] Processing clips 101-105/264...\n[16:26:32] Processing clips 106-110/264...\n[16:26:33] Processing clips 111-115/264...\n[16:26:34] Processing clips 116-120/264...\n[16:26:35] Processing clips 121-125/264...", "timestamp": 1766334395.569456}