{"progress": 69, "message": "Completed 98/246 clips", "status": "processing", "logs": "[16:59:31] Completed 69/246 clips\n[16:59:33] Completed 70/246 clips\n[16:59:34] Completed 71/246 clips\n[16:59:37] Completed 72/246 clips\n[16:59:40] Completed 73/246 clips\n[16:59:41] Completed 74/246 clips\n[16:59:44] Completed 75/246 clips\n[16:59:45] Completed 76/246 clips\n[16:59:46] Completed 77/246 clips\n[16:59:50] Completed 78/246 clips\n[16:59:52] Completed 79/246 clips\n[16:59:53] Completed 80/246 clips\n[16:59:54] Completed 81/246 clips\n[16:59:55] Completed 82/246 clips\n[16:59:57] Completed 83/246 clips\n[17:00:02] Completed 84/246 clips\n[17:00:03] Completed 85/246 clips\n[17:00:04] Completed 86/246 clips\n[17:00:05] Completed 87/246 clips\n[17:00:07] Completed 88/246 clips\n[17:00:09] Completed 89/246 clips\n[17:00:10] Completed 90/246 clips\n[17:00:12] Completed 91/246 clips\n[17:00:14] Completed 92/246 clips\n[17:00:17] Completed 93/246 clips\n[17:00:19] Completed 94/246 clips\n[17:00:21] Completed 95/246 clips\n[17:00:22] Completed 96/246 clips\n[17:00:23] Completed 97/246 clips\n[17:00:24] Completed 98/246 clips", "timestamp": 1768496424.1603756}