{"progress": 64, "message": "Completed 38/234 clips", "status": "processing", "logs": "[07:27:36] Completed 9/234 clips\n[07:27:37] Completed 10/234 clips\n[07:27:39] Completed 11/234 clips\n[07:27:40] Completed 12/234 clips\n[07:27:41] Completed 13/234 clips\n[07:27:43] Completed 14/234 clips\n[07:27:45] Completed 15/234 clips\n[07:27:46] Completed 16/234 clips\n[07:27:47] Completed 17/234 clips\n[07:27:49] Completed 18/234 clips\n[07:27:50] Completed 19/234 clips\n[07:27:53] Completed 20/234 clips\n[07:27:54] Completed 21/234 clips\n[07:27:56] Completed 22/234 clips\n[07:27:57] Completed 23/234 clips\n[07:27:58] Completed 24/234 clips\n[07:27:59] Completed 25/234 clips\n[07:28:02] Completed 26/234 clips\n[07:28:04] Completed 27/234 clips\n[07:28:05] Completed 28/234 clips\n[07:28:06] Completed 29/234 clips\n[07:28:08] Completed 30/234 clips\n[07:28:09] Completed 31/234 clips\n[07:28:11] Completed 32/234 clips\n[07:28:13] Completed 33/234 clips\n[07:28:14] Completed 34/234 clips\n[07:28:16] Completed 35/234 clips\n[07:28:17] Completed 36/234 clips\n[07:28:18] Completed 37/234 clips\n[07:28:20] Completed 38/234 clips", "timestamp": 1768375700.3154616}