{"progress": 75, "message": "Completed 154/245 clips", "status": "processing", "logs": "[16:44:46] Completed 125/245 clips\n[16:44:47] Completed 126/245 clips\n[16:44:49] Completed 127/245 clips\n[16:44:49] Completed 128/245 clips\n[16:44:51] Completed 129/245 clips\n[16:44:54] Completed 130/245 clips\n[16:44:57] Completed 131/245 clips\n[16:44:59] Completed 132/245 clips\n[16:45:00] Completed 133/245 clips\n[16:45:01] Completed 134/245 clips\n[16:45:03] Completed 135/245 clips\n[16:45:05] Completed 136/245 clips\n[16:45:07] Completed 137/245 clips\n[16:45:10] Completed 138/245 clips\n[16:45:11] Completed 139/245 clips\n[16:45:12] Completed 140/245 clips\n[16:45:13] Completed 141/245 clips\n[16:45:15] Completed 142/245 clips\n[16:45:18] Completed 143/245 clips\n[16:45:18] Completed 144/245 clips\n[16:45:21] Completed 145/245 clips\n[16:45:23] Completed 146/245 clips\n[16:45:24] Completed 147/245 clips\n[16:45:26] Completed 148/245 clips\n[16:45:27] Completed 149/245 clips\n[16:45:29] Completed 150/245 clips\n[16:45:31] Completed 151/245 clips\n[16:45:32] Completed 152/245 clips\n[16:45:34] Completed 153/245 clips\n[16:45:35] Completed 154/245 clips", "timestamp": 1768495535.0103004}