{"progress": 72, "message": "Completed 102/205 clips", "status": "processing", "logs": "[09:01:03] Completed 73/205 clips\n[09:01:04] Completed 74/205 clips\n[09:01:07] Completed 75/205 clips\n[09:01:08] Completed 76/205 clips\n[09:01:09] Completed 77/205 clips\n[09:01:10] Completed 78/205 clips\n[09:01:10] Completed 79/205 clips\n[09:01:11] Completed 80/205 clips\n[09:01:15] Completed 81/205 clips\n[09:01:17] Completed 82/205 clips\n[09:01:17] Completed 83/205 clips\n[09:01:18] Completed 84/205 clips\n[09:01:20] Completed 85/205 clips\n[09:01:21] Completed 86/205 clips\n[09:01:23] Completed 87/205 clips\n[09:01:24] Completed 88/205 clips\n[09:01:25] Completed 89/205 clips\n[09:01:29] Completed 90/205 clips\n[09:01:32] Completed 91/205 clips\n[09:01:33] Completed 92/205 clips\n[09:01:34] Completed 93/205 clips\n[09:01:35] Completed 94/205 clips\n[09:01:36] Completed 95/205 clips\n[09:01:42] Completed 96/205 clips\n[09:01:43] Completed 97/205 clips\n[09:01:44] Completed 98/205 clips\n[09:01:46] Completed 99/205 clips\n[09:01:47] Completed 100/205 clips\n[09:01:48] Completed 101/205 clips\n[09:01:54] Completed 102/205 clips", "timestamp": 1766653314.8630025}