{"progress": 82, "message": "Completed 278/309 clips", "status": "processing", "logs": "[14:42:51] Completed 249/309 clips\n[14:42:53] Completed 250/309 clips\n[14:42:54] Completed 251/309 clips\n[14:42:55] Completed 252/309 clips\n[14:42:57] Completed 253/309 clips\n[14:42:58] Completed 254/309 clips\n[14:43:01] Completed 255/309 clips\n[14:43:02] Completed 256/309 clips\n[14:43:04] Completed 257/309 clips\n[14:43:06] Completed 258/309 clips\n[14:43:07] Completed 259/309 clips\n[14:43:08] Completed 260/309 clips\n[14:43:10] Completed 261/309 clips\n[14:43:11] Completed 262/309 clips\n[14:43:12] Completed 263/309 clips\n[14:43:17] Completed 264/309 clips\n[14:43:18] Completed 265/309 clips\n[14:43:19] Completed 266/309 clips\n[14:43:21] Completed 267/309 clips\n[14:43:22] Completed 268/309 clips\n[14:43:24] Completed 269/309 clips\n[14:43:26] Completed 270/309 clips\n[14:43:27] Completed 271/309 clips\n[14:43:28] Completed 272/309 clips\n[14:43:29] Completed 273/309 clips\n[14:43:30] Completed 274/309 clips\n[14:43:31] Completed 275/309 clips\n[14:43:34] Completed 276/309 clips\n[14:43:35] Completed 277/309 clips\n[14:43:37] Completed 278/309 clips", "timestamp": 1768142617.1933348}